nobi_dl/__init__.py
nobi_dl/__main__.py
nobi_dl/common.py
nobi_dl/format_render.py
nobi_dl/host_finder.py
nobi_dl/logger.py
nobi_dl/nobi_dl.py
nobi_dl/options.py
nobi_dl/search.py
nobi_dl/utils.py
nobi_dl/version.py
nobi_dl/downloader/__init__.py
nobi_dl/downloader/common.py
nobi_dl/downloader/downloader.py
nobi_dl/downloader/fmt_resolver.py
nobi_dl/downloader/hls.py
nobi_dl/downloader/http.py
nobi_dl/extractors/bollyflix.py
nobi_dl/extractors/extractors.py
nobi_dl/extractors/fourkhdhub.py
nobi_dl/extractors/hdhub.py
nobi_dl/extractors/moviesmod.py
nobi_dl/extractors/vegamovies.py
nobi_dl/networking/__init__.py
nobi_dl/networking/_curl_cffi.py
nobi_dl/networking/_request.py
nobi_dl/networking/_request_handler.py
nobi_dl/networking/_urllib.py
nobi_dl-2026.1.32.dist-info/licenses/LICENSE
nobi_dl-2026.1.32.dist-info/METADATA
nobi_dl-2026.1.32.dist-info/WHEEL
nobi_dl-2026.1.32.dist-info/entry_points.txt
nobi_dl-2026.1.32.dist-info/top_level.txt
nobi_dl-2026.1.32.dist-info/RECORD
