Metadata-Version: 2.4
Name: nobi-dl
Version: 2026.1.32
Summary: A scraping-based movie downloader. No own database; sources are scraped from the web.
Author-email: 0xvd <0xvd12@gmail.com>
License-Expression: MIT
Project-URL: Homepage, https://github.com/0xvd/nobi-dl
Project-URL: Source, https://github.com/0xvd/nobi-dl
Project-URL: Issues, https://github.com/0xvd/nobi-dl/issues
Requires-Python: >=3.10
License-File: LICENSE
Requires-Dist: requests>=2.25
Provides-Extra: curl
Requires-Dist: curl-cffi>=0.7; extra == "curl"
Provides-Extra: fuzzy
Requires-Dist: rapidfuzz>=3.0; extra == "fuzzy"
Provides-Extra: dev
Requires-Dist: build; extra == "dev"
Requires-Dist: twine; extra == "dev"
Dynamic: license-file
